README.md
setup.cfg
setup.py
query_client_silverbullet_s.egg-info/PKG-INFO
query_client_silverbullet_s.egg-info/SOURCES.txt
query_client_silverbullet_s.egg-info/dependency_links.txt
query_client_silverbullet_s.egg-info/requires.txt
query_client_silverbullet_s.egg-info/top_level.txt
samp_client_ES/__init__.py
samp_client_ES/client.py
samp_client_ES/constants.py
samp_client_ES/exceptions.py
samp_client_ES/models.py
samp_client_ES/utils.py