Metadata-Version: 2.1
Name: query-client-silverbullet-s
Version: 1.0.3
Summary: SA-MP API client for python supporting both query and RCON APIs
Home-page: https://github.com/thenooblol2003/samp-client-s
Author: Michal Dabski
Author-email: contact@michaldabski.com
License: MIT
Download-URL: https://github.com/thenooblol2003/samp-client-s/archive/1.0.3.tar.gz
Platform: UNKNOWN
